bw_hestia_bridge/__init__.py
bw_hestia_bridge/importer.py
bw_hestia_bridge/data/ecoinvent_mappings_biosphere.csv
bw_hestia_bridge/data/ecoinvent_mappings_technosphere.csv
bw_hestia_bridge/hestia_api/__init__.py
bw_hestia_bridge/hestia_api/base_api.py
bw_hestia_bridge/hestia_api/cycle_graph.py
bw_hestia_bridge/hestia_api/querying.py
bw_hestia_bridge/strategies/__init__.py
bw_hestia_bridge/strategies/conversion.py
bw_hestia_bridge/strategies/generic.py
bw_hestia_bridge/strategies/linking.py
bw_hestia_bridge/utils/__init__.py
bw_hestia_bridge/utils/config.py
bw_hestia_bridge-0.3.1.dist-info/LICENSE
bw_hestia_bridge-0.3.1.dist-info/METADATA
bw_hestia_bridge-0.3.1.dist-info/WHEEL
bw_hestia_bridge-0.3.1.dist-info/top_level.txt
bw_hestia_bridge-0.3.1.dist-info/RECORD
