Metadata-Version: 2.1
Name: bw-hestia-bridge
Version: 0.3.1
Summary: Import HESTIA data directly into Brightway
Author: Timo Diepers, Tanguy Fardet, Clemens Wingenbach
Author-email: Chris Mutel <cmutel@gmail.com>
Maintainer-email: Chris Mutel <cmutel@gmail.com>
Project-URL: source, https://github.com/brightway-lca/bw_hestia_bridge
Project-URL: homepage, https://github.com/brightway-lca/bw_hestia_bridge
Project-URL: tracker, https://github.com/brightway-lca/bw_hestia_bridge/issues
Keywords: brightway,hestia,agriculture,development
Classifier: Development Status :: 3 - Alpha
Classifier: Intended Audience :: Science/Research
Classifier: License :: OSI Approved :: MIT License
Classifier: Natural Language :: English
Classifier: Programming Language :: Python :: 3
Classifier: Operating System :: OS Independent
Classifier: Topic :: Scientific/Engineering
Requires-Python: >=3.9
License-File: LICENSE
Requires-Dist: bw2data >=4.0.dev29
Requires-Dist: bw2io >=0.9.DEV23
Requires-Dist: platformdirs
Requires-Dist: requests
Requires-Dist: constructive-geometries
Provides-Extra: dev
Requires-Dist: pre-commit ; extra == 'dev'
Requires-Dist: pylint ; extra == 'dev'
Provides-Extra: docs
Requires-Dist: ipython ; extra == 'docs'
Requires-Dist: pydata-sphinx-theme ; extra == 'docs'
Requires-Dist: myst-parser ; extra == 'docs'
Requires-Dist: sphinx-click ; extra == 'docs'
Requires-Dist: sphinx-design ; extra == 'docs'
Requires-Dist: sphinx-notfound-page ; extra == 'docs'
Requires-Dist: sphinx-favicon ; extra == 'docs'
Requires-Dist: sphinx-copybutton ; extra == 'docs'
Requires-Dist: sphinx-autobuild ; extra == 'docs'
Provides-Extra: testing
Requires-Dist: setuptools ; extra == 'testing'
Requires-Dist: pytest ; extra == 'testing'
Requires-Dist: pytest-cov ; extra == 'testing'
